dustyn/__init__.py
dustyn/_typing.py
dustyn/disk.py
dustyn/sswind_models.py
dustyn/core/__init__.py
dustyn/core/algebra.py
dustyn/core/evolve.py
dustyn/core/integrate.py
dustyn/core/medium.py
dustyn/core/newton.py
dustyn/core/progress.py
dustyn/core/record.py
dustyn/core/sampling.py
dustyn/core/transform.py
dustyn/plot/__init__.py
dustyn/plot/background.py
dustyn/plot/record_plot.py
dustyn/plot/trajectory.py
dustyn-0.2.2.dist-info/LICENSE
dustyn-0.2.2.dist-info/METADATA
dustyn-0.2.2.dist-info/WHEEL
dustyn-0.2.2.dist-info/top_level.txt
dustyn-0.2.2.dist-info/RECORD
