Metadata-Version: 2.1
Name: dustyn
Version: 0.2.2
Summary: UNKNOWN
Home-page: https://github.com/neutrinoceros/dustyn
Author: C.M.T. Robert
License: GPL-2.0
Platform: UNKNOWN
Classifier: License :: OSI Approved :: GNU General Public License v2 (GPLv2)
Classifier: Programming Language :: Python :: 3
Classifier: Programming Language :: Python :: 3 :: Only
Classifier: Programming Language :: Python :: 3.9
Classifier: Programming Language :: Python :: 3.10
Requires-Python: >=3.9
License-File: LICENSE
Requires-Dist: matplotlib (>=3.4)
Requires-Dist: more-itertools (>=8.7.0)
Requires-Dist: numpy (>=1.20)
Requires-Dist: rich (>=10.0.0)
Requires-Dist: scipy (>=1.7.0)
Requires-Dist: sympy (>=1.7.1)
Provides-Extra: dev
Requires-Dist: hypothesis (>=6.2.0<7.0) ; extra == 'dev'
Requires-Dist: pytest (>=6.2.2<7.0) ; extra == 'dev'
Requires-Dist: pytest-cov ; extra == 'dev'
Requires-Dist: pytest-mpl (>=0.12) ; extra == 'dev'
Requires-Dist: requests (>=1.21.1) ; extra == 'dev'
